bidir/__init__.py
bidir/bidir.py
FStitch_Bidir-0.2.dist-info/METADATA
FStitch_Bidir-0.2.dist-info/WHEEL
FStitch_Bidir-0.2.dist-info/entry_points.txt
FStitch_Bidir-0.2.dist-info/top_level.txt
FStitch_Bidir-0.2.dist-info/RECORD
